EXCEL_COLUMN_TO_DECIMAL_CONVERTER/excel_column_to_decimal_converter.py
EXCEL_COLUMN_TO_DECIMAL_CONVERTER-1.dist-info/LICENSE
EXCEL_COLUMN_TO_DECIMAL_CONVERTER-1.dist-info/METADATA
EXCEL_COLUMN_TO_DECIMAL_CONVERTER-1.dist-info/WHEEL
EXCEL_COLUMN_TO_DECIMAL_CONVERTER-1.dist-info/entry_points.txt
EXCEL_COLUMN_TO_DECIMAL_CONVERTER-1.dist-info/top_level.txt
EXCEL_COLUMN_TO_DECIMAL_CONVERTER-1.dist-info/RECORD
