Metadata-Version: 2.1
Name: EXCEL-COLUMN-TO-DECIMAL-CONVERTER
Version: 1
Summary: This library is a simple library to convert Excel column to decimal.
Home-page: https://github.com/GlobalCreativeApkDev/GlobalCreativeApkDev.github.io/tree/main/programming-libraries/EXCEL_COLUMN_TO_DECIMAL_CONVERTER
Author: GlobalCreativeApkDev
Author-email: globalcreativeapkdev2022@gmail.com
License: MIT
Classifier: Programming Language :: Python :: 3
Classifier: Programming Language :: Python :: 3.7
License-File: LICENSE
